LICENSE.md
MANIFEST.in
README.md
setup.py
CModules/LinAlg.c
CModules/LinAlg.h
CModules/wrapper3.c
CellConstructor.egg-info/PKG-INFO
CellConstructor.egg-info/SOURCES.txt
CellConstructor.egg-info/dependency_links.txt
CellConstructor.egg-info/top_level.txt
FModules/constants.f90
FModules/contract_two_phonon_propagator.f90
FModules/cryst_to_car.f90
FModules/eff_charge_interp.f90
FModules/eqvect.f90
FModules/error_handler.f90
FModules/fc_supercell_from_dyn.f90
FModules/flush_unit.f90
FModules/from_matdyn.f90
FModules/get_equivalent_atoms.f90
FModules/get_latvec.f90
FModules/get_lf.f90
FModules/get_q_grid_fast.f90
FModules/get_scattering_q_grid.f90
FModules/get_translations.f90
FModules/interp.f90
FModules/invmat.f90
FModules/io_global.f90
FModules/kind.f90
FModules/q2qstar_out.f90
FModules/q_gen.f90
FModules/recips.f90
FModules/rotate_and_add_dyn.f90
FModules/second_order_ASR.f90
FModules/second_order_centering.f90
FModules/set_asr.f90
FModules/set_tau.f90
FModules/sgam_ph.f90
FModules/smallgq.f90
FModules/star_q.f90
FModules/symdynph_gq_new.f90
FModules/symm_base.f90
FModules/symm_matrix.f90
FModules/symmetry_high_rank.f90
FModules/symvector.f90
FModules/third_order_ASR.f90
FModules/third_order_centering.f90
FModules/third_order_cond.f90
FModules/third_order_cond_centering.f90
FModules/third_order_dynbubble.f90
FModules/third_order_interpol.f90
FModules/trntnsc.f90
FModules/unwrap_tensors.f90
cellconstructor/AnharmonicForceFields.py
cellconstructor/Bands.py
cellconstructor/ForceTensor.py
cellconstructor/Manipulate.py
cellconstructor/Methods.py
cellconstructor/Moro_object.py
cellconstructor/Phonons.py
cellconstructor/Settings.py
cellconstructor/Spectral.py
cellconstructor/Structure.py
cellconstructor/ThermalConductivity.py
cellconstructor/Timer.py
cellconstructor/Units.py
cellconstructor/__init__.py
cellconstructor/calculators.py
cellconstructor/symmetries.py
cellconstructor/SymData/15.dat
cellconstructor/SymData/36.dat
cellconstructor/SymData/36_red.dat
cellconstructor/SymData/60.dat
cellconstructor/SymData/64.bcs
cellconstructor/SymData/64.dat
cellconstructor/SymData/convert_sym.py
scripts/cellconstructor_test.py
