Metadata-Version: 2.1
Name: CellConstructor
Version: 1.3.1
Summary: Python utilities that is interfaced with ASE for atomic crystal analysis
Home-page: https://github.com/mesonepigreco/CellConstructor
Author: Lorenzo Monacelli
License: MIT
License-File: LICENSE.md
